ipumspy/__init__.py
ipumspy/__version__.py
ipumspy/api/__init__.py
ipumspy/api/core.py
ipumspy/api/exceptions.py
ipumspy/api/extract.py
ipumspy/api/metadata.py
ipumspy/cli.py
ipumspy/data/__init__.py
ipumspy/data/nyts.yml.gz
ipumspy/data/yrbss.yml.gz
ipumspy/ddi.py
ipumspy/fileutils.py
ipumspy/noextract.py
ipumspy/readers.py
ipumspy/types.py
ipumspy/utilities.py
ipumspy-0.7.0.dist-info/LICENSE
ipumspy-0.7.0.dist-info/METADATA
ipumspy-0.7.0.dist-info/WHEEL
ipumspy-0.7.0.dist-info/entry_points.txt
ipumspy-0.7.0.dist-info/RECORD
